touchprice/__init__.py
touchprice/condition.py
touchprice/constant.py
touchprice/core.py
touchprice/touch_price.py
touchprice-0.1.8.dist-info/METADATA
touchprice-0.1.8.dist-info/WHEEL
touchprice-0.1.8.dist-info/RECORD
