Metadata-Version: 2.1
Name: touchprice
Version: 0.1.8
Summary: shioaji touchprice extentions
Author: Sally
Author-email: nipolikae@gmail.com
Requires-Python: >=3.7,<4.0
Classifier: Programming Language :: Python :: 3
Classifier: Programming Language :: Python :: 3.7
Classifier: Programming Language :: Python :: 3.8
Classifier: Programming Language :: Python :: 3.9
Classifier: Programming Language :: Python :: 3.10
Classifier: Programming Language :: Python :: 3.11
Requires-Dist: pydantic (>=2.0,<3.0)
Requires-Dist: requests (==2.22.0)
Requires-Dist: shioaji (>=1.0,<2.0)
